{
"type":"FeatureCollection",
"features":
[
{"type":"Feature","properties":{"id": 1, "parkplaetze": 95, "verkaufsflaeche": 969},"geometry":{"type":"Point","coordinates":[13.370704650878906,52.540867042871824]}},
{"type":"Feature","properties":{"id": 2, "parkplaetze": 44, "verkaufsflaeche": 909},"geometry":{"type":"Point","coordinates":[13.454132080078125,52.51642978796417]}},
{"type":"Feature","properties":{"id": 3, "parkplaetze": 43, "verkaufsflaeche": 1031},"geometry":{"type":"Point","coordinates":[13.495330810546875,52.56591677100683]}},
{"type":"Feature","properties":{"id": 4, "parkplaetze": 60, "verkaufsflaeche": 951},"geometry":{"type":"Point","coordinates":[13.563995361328125,52.49239701180824]}},
{"type":"Feature","properties":{"id": 5, "parkplaetze": 73, "verkaufsflaeche": 816},"geometry":{"type":"Point","coordinates":[13.525199890136717,52.53063429179508]}},
{"type":"Feature","properties":{"id": 6, "parkplaetze": 32, "verkaufsflaeche": 871},"geometry":{"type":"Point","coordinates":[13.495330810546875,52.449314140869696]}},
{"type":"Feature","properties":{"id": 7, "parkplaetze": 37, "verkaufsflaeche": 817},"geometry":{"type":"Point","coordinates":[13.385467529296875,52.443245689730304]}},
{"type":"Feature","properties":{"id": 8, "parkplaetze": 98, "verkaufsflaeche": 988},"geometry":{"type":"Point","coordinates":[13.325042724609375,52.46709616449352]}},
{"type":"Feature","properties":{"id": 9, "parkplaetze": 91, "verkaufsflaeche": 950},"geometry":{"type":"Point","coordinates":[13.310623168945312,52.51099744023003]}},
{"type":"Feature","properties":{ "id": 10, "parkplaetze": 84, "verkaufsflaeche": 956},"geometry":{"type":"Point","coordinates":[13.368988037109375,52.48612543090344]}},
{"type":"Feature","properties":{"id": 11, "parkplaetze": 62, "verkaufsflaeche": 1047},"geometry":{"type":"Point","coordinates":[13.383064270019531,52.513295823153165]}},
{"type":"Feature","properties":{"id": 12, "parkplaetze": 99, "verkaufsflaeche": 1001},"geometry":{"type":"Point","coordinates":[13.416366577148438,52.54358145411929]}},
{"type":"Feature","properties":{"id": 13, "parkplaetze": 46, "verkaufsflaeche": 1075},"geometry":{"type":"Point","coordinates":[13.430442810058594,52.46835109482059]}},
{"type":"Feature","properties":{"id": 14, "parkplaetze": 74, "verkaufsflaeche": 1015},"geometry":{"type":"Point","coordinates":[13.414306640625,52.49866769844086]}},
{"type":"Feature","properties":{"id": 15, "parkplaetze": 69, "verkaufsflaeche": 960},"geometry":{"type":"Point","coordinates":[13.483314514160154,52.48591636280465]}},
{"type":"Feature","properties":{"id": 16, "parkplaetze": 90, "verkaufsflaeche": 1023},"geometry":{"type":"Point","coordinates":[13.419456481933594,52.52207036136366]}},
{"type":"Feature","properties":{"id": 17, "parkplaetze": 83, "verkaufsflaeche": 984},"geometry":{"type":"Point","coordinates":[13.501167297363281,52.51225111854443]}},
{"type":"Feature","properties":{"id": 18, "parkplaetze": 69, "verkaufsflaeche": 1055},"geometry":{"type":"Point","coordinates":[13.517990112304688,52.477552824001755]}},
{"type":"Feature","properties":{"id": 19, "parkplaetze": 83, "verkaufsflaeche": 933},"geometry":{"type":"Point","coordinates":[13.438339233398436,52.44240859637802]}},
{"type":"Feature","properties":{"id": 20, "parkplaetze": 29, "verkaufsflaeche": 955},"geometry":{"type":"Point","coordinates":[13.302040100097654,52.49866769844086]}},
{"type":"Feature","properties":{"id": 21, "parkplaetze": 76, "verkaufsflaeche": 1023},"geometry":{"type":"Point","coordinates":[13.338432312011719,52.52917227553519]}},
{"type":"Feature","properties":{"id": 22, "parkplaetze": 61, "verkaufsflaeche": 914},"geometry":{"type":"Point","coordinates":[13.369331359863281,52.564873317831044]}},
{"type":"Feature","properties":{"id": 23, "parkplaetze": 67, "verkaufsflaeche": 801},"geometry":{"type":"Point","coordinates":[13.458595275878906,52.549218541178455]}},
{"type":"Feature","properties":{"id": 24, "parkplaetze": 41, "verkaufsflaeche": 964},"geometry":{"type":"Point","coordinates":[13.394393920898438,52.477343715159854]}},
{"type":"Feature","properties":{"id": 25, "parkplaetze": 88, "verkaufsflaeche": 1079},"geometry":{"type":"Point","coordinates":[13.469924926757812,52.4639586821403]}},
{"type":"Feature","properties":{"id": 26, "parkplaetze": 56, "verkaufsflaeche": 1010},"geometry":{"type":"Point","coordinates":[13.478507995605469,52.53376701989025]}},
{"type":"Feature","properties":{"id": 27, "parkplaetze": 61, "verkaufsflaeche": 916},"geometry":{"type":"Point","coordinates":[13.342208862304688,52.50201169900509]}},
  {
    "type": "Feature",
    "properties": {"id": 27, "parkplaetze": 35, "verkaufsflaeche": 929},
    "geometry": {
      "type": "Point",
      "coordinates": [
        13.333282470703125,
        52.555898595759395
      ]
    }
  },
  {
    "type": "Feature",
    "properties": {"id": 28, "parkplaetze": 53, "verkaufsflaeche": 958},
    "geometry": {
      "type": "Point",
      "coordinates": [
        13.303070068359375,
        52.54587813253921
      ]
    }
  },
  {
    "type": "Feature",
    "properties": {"id": 29, "parkplaetze": 40, "verkaufsflaeche": 967},
    "geometry": {
      "type": "Point",
      "coordinates": [
        13.333969116210938,
        52.579688026538726
      ]
    }
  },
  {
    "type": "Feature",
    "properties": {"id": 30, "parkplaetze": 39, "verkaufsflaeche": 888},
    "geometry": {
      "type": "Point",
      "coordinates": [
        13.291397094726562,
        52.57175965005525
      ]
    }
  },
  {
    "type": "Feature",
    "properties": {"id": 31, "parkplaetze": 53, "verkaufsflaeche": 879},
    "geometry": {
      "type": "Point",
      "coordinates": [
        13.30787658691406,
        52.60054532499603
      ]
    }
  },
  {
    "type": "Feature",
    "properties": {"id": 32, "parkplaetze": 71, "verkaufsflaeche": 871},
    "geometry": {
      "type": "Point",
      "coordinates": [
        13.26324462890625,
        52.59804297332564
      ]
    }
  },
  {
    "type": "Feature",
    "properties": {"id": 33, "parkplaetze": 44, "verkaufsflaeche": 940},
    "geometry": {
      "type": "Point",
      "coordinates": [
        13.275604248046873,
        52.623476888560916
      ]
    }
  },
  {
    "type": "Feature",
    "properties": {"id": 34, "parkplaetze": 40, "verkaufsflaeche": 820},
    "geometry": {
      "type": "Point",
      "coordinates": [
        13.295516967773438,
        52.65139547872391
      ]
    }
  },
  {
    "type": "Feature",
    "properties": {"id": 35, "parkplaetze": 70, "verkaufsflaeche": 905},
    "geometry": {
      "type": "Point",
      "coordinates": [
        13.352508544921875,
        52.61805778461654
      ]
    }
  },
  {
    "type": "Feature",
    "properties": {"id": 36, "parkplaetze": 97, "verkaufsflaeche": 847},
    "geometry": {
      "type": "Point",
      "coordinates": [
        13.36830139160156,
        52.60054532499603
      ]
    }
  },
  {
    "type": "Feature",
    "properties": {"id": 37, "parkplaetze": 86, "verkaufsflaeche": 899},
    "geometry": {
      "type": "Point",
      "coordinates": [
        13.395767211914062,
        52.561742809358755
      ]
    }
  },
  {
    "type": "Feature",
    "properties": {"id": 38, "parkplaetze": 61, "verkaufsflaeche": 803},
    "geometry": {
      "type": "Point",
      "coordinates": [
        13.382720947265625,
        52.59053506065283
      ]
    }
  },
  {
    "type": "Feature",
    "properties": {"id": 39, "parkplaetze": 61, "verkaufsflaeche": 973},
    "geometry": {
      "type": "Point",
      "coordinates": [
        13.399200439453125,
        52.621392697207625
      ]
    }
  },
  {
    "type": "Feature",
    "properties": {"id": 40, "parkplaetze": 61, "verkaufsflaeche": 909},
    "geometry": {
      "type": "Point",
      "coordinates": [
        13.421173095703125,
        52.585111879151945
      ]
    }
  },
  {
    "type": "Feature",
    "properties": {"id": 41, "parkplaetze": 61, "verkaufsflaeche": 986},
    "geometry": {
      "type": "Point",
      "coordinates": [
        13.430099487304688,
        52.61180413870482
      ]
    }
  },
  {
    "type": "Feature",
    "properties": {"id": 42, "parkplaetze": 61, "verkaufsflaeche": 879},
    "geometry": {
      "type": "Point",
      "coordinates": [
        13.432159423828125,
        52.56758624445477
      ]
    }
  },
  {
    "type": "Feature",
    "properties": {"id": 43, "parkplaetze": 61, "verkaufsflaeche": 858},
    "geometry": {
      "type": "Point",
      "coordinates": [
        13.454818725585938,
        52.60221348003281
      ]
    }
  },
  {
    "type": "Feature",
    "properties": {"id": 44, "parkplaetze": 61, "verkaufsflaeche": 841},
    "geometry": {
      "type": "Point",
      "coordinates": [
        13.463745117187498,
        52.58386028042404
      ]
    }
  },
  {
    "type": "Feature",
    "properties": {"id": 45, "parkplaetze": 61, "verkaufsflaeche": 980},
    "geometry": {
      "type": "Point",
      "coordinates": [
        13.462371826171875,
        52.57217696877135
      ]
    }
  },
  {
    "type": "Feature",
    "properties": {"id": 46, "parkplaetze": 61, "verkaufsflaeche": 847},
    "geometry": {
      "type": "Point",
      "coordinates": [
        13.480911254882812,
        52.60596659659655
      ]
    }
  },
  {
    "type": "Feature",
    "properties": {"id": 47, "parkplaetze": 61, "verkaufsflaeche": 975},
    "geometry": {
      "type": "Point",
      "coordinates": [
        13.44451904296875,
        52.634313083880016
      ]
    }
  },
  {
    "type": "Feature",
    "properties": {"id": 48, "parkplaetze": 61, "verkaufsflaeche": 821},
    "geometry": {
      "type": "Point",
      "coordinates": [
        13.478851318359375,
        52.64472997207245
      ]
    }
  },
  {
    "type": "Feature",
    "properties": {"id": 49, "parkplaetze": 61, "verkaufsflaeche": 956},
    "geometry": {
      "type": "Point",
      "coordinates": [
        13.500137329101562,
        52.63556324144265
      ]
    }
  },
  {
    "type": "Feature",
    "properties": {"id": 50, "parkplaetze": 61, "verkaufsflaeche": 894},
    "geometry": {
      "type": "Point",
      "coordinates": [
        13.489837646484375,
        52.59303784115741
      ]
    }
  },
  {
    "type": "Feature",
    "properties": {"id": 51, "parkplaetze": 61, "verkaufsflaeche": 934},
    "geometry": {
      "type": "Point",
      "coordinates": [
        13.52691650390625,
        52.580522509085554
      ]
    }
  },
  {
    "type": "Feature",
    "properties": {"id": 52, "parkplaetze": 61, "verkaufsflaeche": 864},
    "geometry": {
      "type": "Point",
      "coordinates": [
        13.504257202148438,
        52.550888650159386
      ]
    }
  },
  {
    "type": "Feature",
    "properties": {"id": 53, "parkplaetze": 61, "verkaufsflaeche": 941},
    "geometry": {
      "type": "Point",
      "coordinates": [
        13.534469604492188,
        52.56257763346352
      ]
    }
  },
  {
    "type": "Feature",
    "properties": {"id": 54, "parkplaetze": 61, "verkaufsflaeche": 807},
    "geometry": {
      "type": "Point",
      "coordinates": [
        13.545455932617188,
        52.549218541178455
      ]
    }
  },
  {
    "type": "Feature",
    "properties": {"id": 55, "parkplaetze": 61, "verkaufsflaeche": 814},
    "geometry": {
      "type": "Point",
      "coordinates": [
        13.55987548828125,
        52.53543771682821
      ]
    }
  },
  {
    "type": "Feature",
    "properties": {"id": 56, "parkplaetze": 61, "verkaufsflaeche": 900},
    "geometry": {
      "type": "Point",
      "coordinates": [
        13.572235107421875,
        52.56883830783746
      ]
    }
  },
  {
    "type": "Feature",
    "properties": {"id": 57, "parkplaetze": 61, "verkaufsflaeche": 869},
    "geometry": {
      "type": "Point",
      "coordinates": [
        13.542709350585936,
        52.51413156895822
      ]
    }
  },
  {
    "type": "Feature",
    "properties": {"id": 58, "parkplaetze": 61, "verkaufsflaeche": 850},
    "geometry": {
      "type": "Point",
      "coordinates": [
        13.57635498046875,
        52.51705655410405
      ]
    }
  },
  {
    "type": "Feature",
    "properties": {"id": 59, "parkplaetze": 61, "verkaufsflaeche": 915},
    "geometry": {
      "type": "Point",
      "coordinates": [
        13.603134155273436,
        52.53961418106945
      ]
    }
  },
  {
    "type": "Feature",
    "properties": {"id": 60, "parkplaetze": 61, "verkaufsflaeche": 876},
    "geometry": {
      "type": "Point",
      "coordinates": [
        13.611373901367188,
        52.5199813445422
      ]
    }
  },
  {
    "type": "Feature",
    "properties": {"id": 61, "parkplaetze": 61, "verkaufsflaeche": 898},
    "geometry": {
      "type": "Point",
      "coordinates": [
        13.590774536132812,
        52.50953477032727
      ]
    }
  },
  {
    "type": "Feature",
    "properties": {"id": 62, "parkplaetze": 61, "verkaufsflaeche": 843},
    "geometry": {
      "type": "Point",
      "coordinates": [
        13.605880737304688,
        52.49699560277579
      ]
    }
  },
  {
    "type": "Feature",
    "properties": {"id": 63, "parkplaetze": 61, "verkaufsflaeche": 968},
    "geometry": {
      "type": "Point",
      "coordinates": [
        13.588027954101562,
        52.482780222078226
      ]
    }
  },
  {
    "type": "Feature",
    "properties": {"id": 64, "parkplaetze": 61, "verkaufsflaeche": 948},
    "geometry": {
      "type": "Point",
      "coordinates": [
        13.612747192382812,
        52.48152570318333
      ]
    }
  },
  {
    "type": "Feature",
    "properties": {"id": 65, "parkplaetze": 61, "verkaufsflaeche": 978},
    "geometry": {
      "type": "Point",
      "coordinates": [
        13.520050048828125,
        52.500339730516934
      ]
    }
  },
  {
    "type": "Feature",
    "properties": {"id": 66, "parkplaetze": 61, "verkaufsflaeche": 955},
    "geometry": {
      "type": "Point",
      "coordinates": [
        13.550949096679688,
        52.48152570318333
      ]
    }
  },
  {
    "type": "Feature",
    "properties": {"id": 67, "parkplaetze": 61, "verkaufsflaeche": 917},
    "geometry": {
      "type": "Point",
      "coordinates": [
        13.552322387695312,
        52.46103016351592
      ]
    }
  },
  {
    "type": "Feature",
    "properties": {"id": 68, "parkplaetze": 61, "verkaufsflaeche": 929},
    "geometry": {
      "type": "Point",
      "coordinates": [
        13.5955810546875,
        52.453498792506736
      ]
    }
  },
  {
    "type": "Feature",
    "properties": {"id": 69, "parkplaetze": 61, "verkaufsflaeche": 825},
    "geometry": {
      "type": "Point",
      "coordinates": [
        13.646392822265625,
        52.452661893987695
      ]
    }
  },
  {
    "type": "Feature",
    "properties": {"id": 70, "parkplaetze": 61, "verkaufsflaeche": 892},
    "geometry": {
      "type": "Point",
      "coordinates": [
        13.71917724609375,
        52.44596613327885
      ]
    }
  },
  {
    "type": "Feature",
    "properties": {"id": 71, "parkplaetze": 61, "verkaufsflaeche": 924},
    "geometry": {
      "type": "Point",
      "coordinates": [
        13.705444335937498,
        52.41414736782131
      ]
    }
  },
  {
    "type": "Feature",
    "properties": {"id": 72, "parkplaetze": 61, "verkaufsflaeche": 798},
    "geometry": {
      "type": "Point",
      "coordinates": [
        13.66973876953125,
        52.39487748111347
      ]
    }
  },
  {
    "type": "Feature",
    "properties": {"id": 73, "parkplaetze": 61, "verkaufsflaeche": 977},
    "geometry": {
      "type": "Point",
      "coordinates": [
        13.59832763671875,
        52.42838491816822
      ]
    }
  },
  {
    "type": "Feature",
    "properties": {"id": 74, "parkplaetze": 61, "verkaufsflaeche": 940},
    "geometry": {
      "type": "Point",
      "coordinates": [
        13.614807128906248,
        52.41163438166172
      ]
    }
  },
  {
    "type": "Feature",
    "properties": {"id": 75, "parkplaetze": 61, "verkaufsflaeche": 805},
    "geometry": {
      "type": "Point",
      "coordinates": [
        13.612060546875,
        52.38901106223458
      ]
    }
  },
  {
    "type": "Feature",
    "properties": {"id": 76, "parkplaetze": 61, "verkaufsflaeche": 853},
    "geometry": {
      "type": "Point",
      "coordinates": [
        13.568115234375,
        52.40995897800503
      ]
    }
  },
  {
    "type": "Feature",
    "properties": {"id": 77, "parkplaetze": 61, "verkaufsflaeche": 799},
    "geometry": {
      "type": "Point",
      "coordinates": [
        13.533782958984375,
        52.44178076592579
      ]
    }
  },
  {
    "type": "Feature",
    "properties": {"id": 78, "parkplaetze": 61, "verkaufsflaeche": 838},
    "geometry": {
      "type": "Point",
      "coordinates": [
        13.4967041015625,
        52.40912125231122
      ]
    }
  },
  {
    "type": "Feature",
    "properties": {"id": 79, "parkplaetze": 61, "verkaufsflaeche": 923},
    "geometry": {
      "type": "Point",
      "coordinates": [
        13.40606689453125,
        52.42168546718757
      ]
    }
  },
  {
    "type": "Feature",
    "properties": {"id": 80, "parkplaetze": 61, "verkaufsflaeche": 814},
    "geometry": {
      "type": "Point",
      "coordinates": [
        13.38409423828125,
        52.399067302933304
      ]
    }
  },
  {
    "type": "Feature",
    "properties": {"id": 81, "parkplaetze": 61, "verkaufsflaeche": 933},
    "geometry": {
      "type": "Point",
      "coordinates": [
        13.33465576171875,
        52.42503531994297
      ]
    }
  },
  {
    "type": "Feature",
    "properties": {"id": 82, "parkplaetze": 61, "verkaufsflaeche": 943},
    "geometry": {
      "type": "Point",
      "coordinates": [
        13.271484375,
        52.42671015087138
      ]
    }
  },
  {
    "type": "Feature",
    "properties": {"id": 83, "parkplaetze": 61, "verkaufsflaeche": 860},
    "geometry": {
      "type": "Point",
      "coordinates": [
        13.283843994140625,
        52.46688700596046
      ]
    }
  },
  {
    "type": "Feature",
    "properties": {"id": 84, "parkplaetze": 61, "verkaufsflaeche": 944},
    "geometry": {
      "type": "Point",
      "coordinates": [
        13.205566406249998,
        52.42587274336118
      ]
    }
  },
  {
    "type": "Feature",
    "properties": {"id": 85, "parkplaetze": 61, "verkaufsflaeche": 932},
    "geometry": {
      "type": "Point",
      "coordinates": [
        13.150634765625,
        52.41330972167801
      ]
    }
  },
  {
    "type": "Feature",
    "properties": {"id": 86, "parkplaetze": 61, "verkaufsflaeche": 807},
    "geometry": {
      "type": "Point",
      "coordinates": [
        13.1121826171875,
        52.42252295423907
      ]
    }
  },
  {
    "type": "Feature",
    "properties": {"id": 87, "parkplaetze": 61, "verkaufsflaeche": 846},
    "geometry": {
      "type": "Point",
      "coordinates": [
        13.13690185546875,
        52.46939684276205
      ]
    }
  },
  {
    "type": "Feature",
    "properties": {"id": 88, "parkplaetze": 61, "verkaufsflaeche": 848},
    "geometry": {
      "type": "Point",
      "coordinates": [
        13.173980712890625,
        52.49114276717071
      ]
    }
  },
  {
    "type": "Feature",
    "properties": {"id": 89, "parkplaetze": 61, "verkaufsflaeche": 931},
    "geometry": {
      "type": "Point",
      "coordinates": [
        13.161621093749998,
        52.58135697574736
      ]
    }
  },
  {
    "type": "Feature",
    "properties": {"id": 90, "parkplaetze": 61, "verkaufsflaeche": 802},
    "geometry": {
      "type": "Point",
      "coordinates": [
        13.235778808593748,
        52.58219142652432
      ]
    }
  },
  {
    "type": "Feature",
    "properties": {"id": 91, "parkplaetze": 61, "verkaufsflaeche": 831},
    "geometry": {
      "type": "Point",
      "coordinates": [
        13.14239501953125,
        52.540449426243796
      ]
    }
  },
  {
    "type": "Feature",
    "properties": {"id": 92, "parkplaetze": 61, "verkaufsflaeche": 911},
    "geometry": {
      "type": "Point",
      "coordinates": [
        13.176727294921875,
        52.56132539134846
      ]
    }
  },
  {
    "type": "Feature",
    "properties": {"id": 93, "parkplaetze": 61, "verkaufsflaeche": 830},
    "geometry": {
      "type": "Point",
      "coordinates": [
        13.179473876953125,
        52.53543771682821
      ]
    }
  },
  {
    "type": "Feature",
    "properties": {"id": 94, "parkplaetze": 61, "verkaufsflaeche": 989},
    "geometry": {
      "type": "Point",
      "coordinates": [
        13.226165771484375,
        52.487797939920966
      ]
    }
  },
  {
    "type": "Feature",
    "properties": {"id": 95, "parkplaetze": 61, "verkaufsflaeche": 950},
    "geometry": {
      "type": "Point",
      "coordinates": [
        13.256378173828125,
        52.51371369804256
      ]
    }
  },
  {
    "type": "Feature",
    "properties": {"id": 96, "parkplaetze": 61, "verkaufsflaeche": 872},
    "geometry": {
      "type": "Point",
      "coordinates": [
        13.26324462890625,
        52.553811187940674
      ]
    }
  },
  {
    "type": "Feature",
    "properties": {"id": 97, "parkplaetze": 61, "verkaufsflaeche": 799},
    "geometry": {
      "type": "Point",
      "coordinates": [
        13.20831298828125,
        52.5270835964481
      ]
    }
  }
]}
